[
 {
  "Identifier": "Wise",
  "PayAccount": "",
  "PayMethodId": "",
  "PayType": "",
  "TradeMethodName": "Wise",
  "TradeMethodShortName": ""
 },
 {
  "Identifier": "Revolut",
  "PayAccount": "",
  "PayMethodId": "",
  "PayType": "",
  "TradeMethodName": "Revolut",
  "TradeMethodShortName": "Revolut"
 },
 {
  "Identifier": "SEPAinstant",
  "PayAccount": "",
  "PayMethodId": "",
  "PayType": "",
  "TradeMethodName": "SEPA Instant",
  "TradeMethodShortName": ""
 },
 {
  "Identifier": "SEPA",
  "PayAccount": "",
  "PayMethodId": "",
  "PayType": "",
  "TradeMethodName": "SEPA (EU) bank transfer",
  "TradeMethodShortName": "SEPA"
 },
 {
  "Identifier": "Paysera",
  "PayAccount": "",
  "PayMethodId": "",
  "PayType": "",
  "TradeMethodName": "Paysera",
  "TradeMethodShortName": ""
 },
 {
  "Identifier": "N26",
  "PayAccount": "",
  "PayMethodId": "",
  "PayType": "",
  "TradeMethodName": "N26",
  "TradeMethodShortName": ""
 },
 {
  "Identifier": "BBVABank",
  "PayAccount": "",
  "PayMethodId": "",
  "PayType": "",
  "TradeMethodName": "BBVA",
  "TradeMethodShortName": "BBVA"
 },
 {
  "Identifier": "ZEN",
  "PayAccount": "",
  "PayMethodId": "",
  "PayType": "",
  "TradeMethodName": "ZEN",
  "TradeMethodShortName": ""
 },
 {
  "Identifier": "BANK",
  "PayAccount": "",
  "PayMethodId": "",
  "PayType": "",
  "TradeMethodName": "Bank Transfer",
  "TradeMethodShortName": "Bank Transfer"
 },
 {
  "Identifier": "Bizum",
  "PayAccount": "",
  "PayMethodId": "",
  "PayType": "",
  "TradeMethodName": "Bizum",
  "TradeMethodShortName": ""
 },
 {
  "Identifier": "Advcash",
  "PayAccount": "",
  "PayMethodId": "",
  "PayType": "",
  "TradeMethodName": "Advcash",
  "TradeMethodShortName": "Advcash"
 },
 {
  "Identifier": "SkrillMoneybookers",
  "PayAccount": "",
  "PayMethodId": "",
  "PayType": "",
  "TradeMethodName": "Skrill (Moneybookers)",
  "TradeMethodShortName": "Skrill"
 },
 {
  "Identifier": "Bunq",
  "PayAccount": "",
  "PayMethodId": "",
  "PayType": "",
  "TradeMethodName": "Bunq",
  "TradeMethodShortName": ""
 },
 {
  "Identifier": "ING",
  "PayAccount": "",
  "PayMethodId": "",
  "PayType": "",
  "TradeMethodName": "ING",
  "TradeMethodShortName": "ING"
 },
 {
  "Identifier": "CaixaBank",
  "PayAccount": "",
  "PayMethodId": "",
  "PayType": "",
  "TradeMethodName": "CaixaBank (Spain)",
  "TradeMethodShortName": ""
 },
 {
  "Identifier": "ABNAMRO",
  "PayAccount": "",
  "PayMethodId": "",
  "PayType": "",
  "TradeMethodName": "ABN AMRO",
  "TradeMethodShortName": "ABN AMRO"
 },
 {
  "Identifier": "BancoSantanderSpain",
  "PayAccount": "",
  "PayMethodId": "",
  "PayType": "",
  "TradeMethodName": "Banco Santander (Spain)",
  "TradeMethodShortName": ""
 },
 {
  "Identifier": "Monobank",
  "PayAccount": "",
  "PayMethodId": "",
  "PayType": "",
  "TradeMethodName": "Monobank",
  "TradeMethodShortName": "Monobank"
 },
 {
  "Identifier": "PrivatBank",
  "PayAccount": "",
  "PayMethodId": "",
  "PayType": "",
  "TradeMethodName": "Privat Bank (Universal Card)",
  "TradeMethodShortName": "Privat Bank"
 },
 {
  "Identifier": "Payeer",
  "PayAccount": "",
  "PayMethodId": "",
  "PayType": "",
  "TradeMethodName": "Payeer",
  "TradeMethodShortName": "Payeer"
 },
 {
  "Identifier": "BancoSabadellSpain",
  "PayAccount": "",
  "PayMethodId": "",
  "PayType": "",
  "TradeMethodName": "Banco Sabadell (Spain)",
  "TradeMethodShortName": ""
 },
 {
  "Identifier": "MAIB",
  "PayAccount": "",
  "PayMethodId": "",
  "PayType": "",
  "TradeMethodName": "MAIB",
  "TradeMethodShortName": ""
 },
 {
  "Identifier": "PerfectMoney",
  "PayAccount": "",
  "PayMethodId": "",
  "PayType": "",
  "TradeMethodName": "Perfect Money",
  "TradeMethodShortName": "Perfect Money"
 },
 {
  "Identifier": "TinkoffNew",
  "PayAccount": "",
  "PayMethodId": "",
  "PayType": "",
  "TradeMethodName": "Tinkoff",
  "TradeMethodShortName": "Tinkoff"
 },
 {
  "Identifier": "NETELLER",
  "PayAccount": "",
  "PayMethodId": "",
  "PayType": "",
  "TradeMethodName": "NETELLER",
  "TradeMethodShortName": "NETELLER"
 },
 {
  "Identifier": "Kapitalbank",
  "PayAccount": "",
  "PayMethodId": "",
  "PayType": "",
  "TradeMethodName": "Kapitalbank",
  "TradeMethodShortName": ""
 },
 {
  "Identifier": "BankofGeorgia",
  "PayAccount": "",
  "PayMethodId": "",
  "PayType": "",
  "TradeMethodName": "Bank of Georgia",
  "TradeMethodShortName": ""
 },
 {
  "Identifier": "MICB",
  "PayAccount": "",
  "PayMethodId": "",
  "PayType": "",
  "TradeMethodName": "MICB",
  "TradeMethodShortName": ""
 },
 {
  "Identifier": "KaspiBank",
  "PayAccount": "",
  "PayMethodId": "",
  "PayType": "",
  "TradeMethodName": "Kaspi Bank",
  "TradeMethodShortName": "Kaspi Bank"
 },
 {
  "Identifier": "Paysend",
  "PayAccount": "",
  "PayMethodId": "",
  "PayType": "",
  "TradeMethodName": "Paysend.com",
  "TradeMethodShortName": "Paysend"
 },
 {
  "Identifier": "RaiffeisenBank",
  "PayAccount": "",
  "PayMethodId": "",
  "PayType": "",
  "TradeMethodName": "Raiffeisenbank",
  "TradeMethodShortName": "Raiffeisenbank"
 },
 {
  "Identifier": "SpecificBank",
  "PayAccount": "",
  "PayMethodId": "",
  "PayType": "",
  "TradeMethodName": "Transfers with specific bank",
  "TradeMethodShortName": "Transfers with specific bank"
 },
 {
  "Identifier": "BNPParibas",
  "PayAccount": "",
  "PayMethodId": "",
  "PayType": "",
  "TradeMethodName": "BNP Paribas",
  "TradeMethodShortName": "BNP Paribas"
 },
 {
  "Identifier": "SWIFT",
  "PayAccount": "",
  "PayMethodId": "",
  "PayType": "",
  "TradeMethodName": "International Wire (SWIFT)",
  "TradeMethodShortName": "International Wire (SWIFT)"
 },
 {
  "Identifier": "VakifBank",
  "PayAccount": "",
  "PayMethodId": "",
  "PayType": "",
  "TradeMethodName": "VakifBank",
  "TradeMethodShortName": ""
 },
 {
  "Identifier": "CashDeposit",
  "PayAccount": "",
  "PayMethodId": "",
  "PayType": "",
  "TradeMethodName": "Cash Deposit to Bank",
  "TradeMethodShortName": "Cash Deposit to Bank"
 },
 {
  "Identifier": "Victoriabank",
  "PayAccount": "",
  "PayMethodId": "",
  "PayType": "",
  "TradeMethodName": "Victoriabank",
  "TradeMethodShortName": ""
 },
 {
  "Identifier": "HalykBank",
  "PayAccount": "",
  "PayMethodId": "",
  "PayType": "",
  "TradeMethodName": "Halyk Bank",
  "TradeMethodShortName": "Halyk Bank"
 },
 {
  "Identifier": "Postepay",
  "PayAccount": "",
  "PayMethodId": "",
  "PayType": "",
  "TradeMethodName": "Postepay",
  "TradeMethodShortName": ""
 },
 {
  "Identifier": "TBCbank",
  "PayAccount": "",
  "PayMethodId": "",
  "PayType": "",
  "TradeMethodName": "TBC Bank",
  "TradeMethodShortName": ""
 },
 {
  "Identifier": "SocieteGenerale",
  "PayAccount": "",
  "PayMethodId": "",
  "PayType": "",
  "TradeMethodName": "Societe Generale",
  "TradeMethodShortName": "Societe Generale"
 },
 {
  "Identifier": "DenizBank",
  "PayAccount": "",
  "PayMethodId": "",
  "PayType": "",
  "TradeMethodName": "DenizBank",
  "TradeMethodShortName": ""
 },
 {
  "Identifier": "AirTM",
  "PayAccount": "",
  "PayMethodId": "",
  "PayType": "",
  "TradeMethodName": "AirTM",
  "TradeMethodShortName": "AirTM"
 },
 {
  "Identifier": "ABank",
  "PayAccount": "",
  "PayMethodId": "",
  "PayType": "",
  "TradeMethodName": "A-Bank",
  "TradeMethodShortName": ""
 },
 {
  "Identifier": "OTPBank",
  "PayAccount": "",
  "PayMethodId": "",
  "PayType": "",
  "TradeMethodName": "OTP Bank",
  "TradeMethodShortName": ""
 },
 {
  "Identifier": "JysanBank",
  "PayAccount": "",
  "PayMethodId": "",
  "PayType": "",
  "TradeMethodName": "Jysan Bank",
  "TradeMethodShortName": ""
 },
 {
  "Identifier": "WesternUnion",
  "PayAccount": "",
  "PayMethodId": "",
  "PayType": "",
  "TradeMethodName": "Western Union",
  "TradeMethodShortName": "Western Union"
 },
 {
  "Identifier": "DukascopyBank",
  "PayAccount": "",
  "PayMethodId": "",
  "PayType": "",
  "TradeMethodName": "Dukascopy Bank",
  "TradeMethodShortName": "Dukascopy Bank"
 },
 {
  "Identifier": "ForteBank",
  "PayAccount": "",
  "PayMethodId": "",
  "PayType": "",
  "TradeMethodName": "ForteBank",
  "TradeMethodShortName": "ForteBank"
 },
 {
  "Identifier": "PriorBank",
  "PayAccount": "",
  "PayMethodId": "",
  "PayType": "",
  "TradeMethodName": "PriorBank",
  "TradeMethodShortName": "PriorBank"
 },
 {
  "Identifier": "AltynBank",
  "PayAccount": "",
  "PayMethodId": "",
  "PayType": "",
  "TradeMethodName": "Altyn Bank",
  "TradeMethodShortName": ""
 },
 {
  "Identifier": "CreditAgricole",
  "PayAccount": "",
  "PayMethodId": "",
  "PayType": "",
  "TradeMethodName": "Credit Agricole",
  "TradeMethodShortName": "Credit Agricole"
 },
 {
  "Identifier": "BanktransferTurkey",
  "PayAccount": "",
  "PayMethodId": "",
  "PayType": "",
  "TradeMethodName": "Bank Transfer (Turkey)",
  "TradeMethodShortName": ""
 },
 {
  "Identifier": "LaBanquepostale",
  "PayAccount": "",
  "PayMethodId": "",
  "PayType": "",
  "TradeMethodName": "La Banque postale",
  "TradeMethodShortName": "La Banque postale"
 },
 {
  "Identifier": "Ziraat",
  "PayAccount": "",
  "PayMethodId": "",
  "PayType": "",
  "TradeMethodName": "Ziraat",
  "TradeMethodShortName": "Ziraat"
 },
 {
  "Identifier": "CenterCreditBank",
  "PayAccount": "",
  "PayMethodId": "",
  "PayType": "",
  "TradeMethodName": "CenterCredit Bank",
  "TradeMethodShortName": "CenterCredit Bank"
 },
 {
  "Identifier": "OPTIMABANK",
  "PayAccount": "",
  "PayMethodId": "",
  "PayType": "",
  "TradeMethodName": "Optima Bank",
  "TradeMethodShortName": ""
 },
 {
  "Identifier": "MoneyGram",
  "PayAccount": "",
  "PayMethodId": "",
  "PayType": "",
  "TradeMethodName": "Moneygram",
  "TradeMethodShortName": "Moneygram"
 },
 {
  "Identifier": "PUMBBank",
  "PayAccount": "",
  "PayMethodId": "",
  "PayType": "",
  "TradeMethodName": "PUMB",
  "TradeMethodShortName": "PUMB"
 },
 {
  "Identifier": "RaiffeisenBankAval",
  "PayAccount": "",
  "PayMethodId": "",
  "PayType": "",
  "TradeMethodName": "Raiffeisen Bank Aval",
  "TradeMethodShortName": ""
 },
 {
  "Identifier": "Millennium",
  "PayAccount": "",
  "PayMethodId": "",
  "PayType": "",
  "TradeMethodName": "Millennium",
  "TradeMethodShortName": "Millennium"
 },
 {
  "Identifier": "VividMoney",
  "PayAccount": "",
  "PayMethodId": "",
  "PayType": "",
  "TradeMethodName": "Vivid Money",
  "TradeMethodShortName": ""
 },
 {
  "Identifier": "QIWI",
  "PayAccount": "",
  "PayMethodId": "",
  "PayType": "",
  "TradeMethodName": "QIWI",
  "TradeMethodShortName": "QIWI"
 },
 {
  "Identifier": "DEMIRBANK",
  "PayAccount": "",
  "PayMethodId": "",
  "PayType": "",
  "TradeMethodName": "DemirBank",
  "TradeMethodShortName": ""
 },
 {
  "Identifier": "KuveytTurk",
  "PayAccount": "",
  "PayMethodId": "",
  "PayType": "",
  "TradeMethodName": "Kuveyt Turk",
  "TradeMethodShortName": "Kuveyt Turk"
 },
 {
  "Identifier": "RosBankNew",
  "PayAccount": "",
  "PayMethodId": "",
  "PayType": "",
  "TradeMethodName": "RosBank",
  "TradeMethodShortName": "RosBank"
 },
 {
  "Identifier": "CREDOBANK",
  "PayAccount": "",
  "PayMethodId": "",
  "PayType": "",
  "TradeMethodName": "Credo Bank",
  "TradeMethodShortName": ""
 },
 {
  "Identifier": "IDBank",
  "PayAccount": "",
  "PayMethodId": "",
  "PayType": "",
  "TradeMethodName": "IDBank",
  "TradeMethodShortName": ""
 },
 {
  "Identifier": "UniCreditRussia",
  "PayAccount": "",
  "PayMethodId": "",
  "PayType": "",
  "TradeMethodName": "UniCredit",
  "TradeMethodShortName": "UniCredit"
 },
 {
  "Identifier": "UNIBANK",
  "PayAccount": "",
  "PayMethodId": "",
  "PayType": "",
  "TradeMethodName": "Unibank",
  "TradeMethodShortName": ""
 },
 {
  "Identifier": "Ameriabank",
  "PayAccount": "",
  "PayMethodId": "",
  "PayType": "",
  "TradeMethodName": "Ameriabank",
  "TradeMethodShortName": ""
 },
 {
  "Identifier": "BAKAIBANK",
  "PayAccount": "",
  "PayMethodId": "",
  "PayType": "",
  "TradeMethodName": "Bakai Bank",
  "TradeMethodShortName": ""
 },
 {
  "Identifier": "EurasianBank",
  "PayAccount": "",
  "PayMethodId": "",
  "PayType": "",
  "TradeMethodName": "Eurasian Bank",
  "TradeMethodShortName": ""
 },
 {
  "Identifier": "ErsteBank",
  "PayAccount": "",
  "PayMethodId": "",
  "PayType": "",
  "TradeMethodName": "Erste Bank",
  "TradeMethodShortName": ""
 },
 {
  "Identifier": "Garanti",
  "PayAccount": "",
  "PayMethodId": "",
  "PayType": "",
  "TradeMethodName": "Garanti",
  "TradeMethodShortName": "Garanti"
 },
 {
  "Identifier": "Ukrsibbank",
  "PayAccount": "",
  "PayMethodId": "",
  "PayType": "",
  "TradeMethodName": "Ukrsibbank",
  "TradeMethodShortName": ""
 },
 {
  "Identifier": "ABBBANK",
  "PayAccount": "",
  "PayMethodId": "",
  "PayType": "",
  "TradeMethodName": "ABB Bank",
  "TradeMethodShortName": ""
 },
 {
  "Identifier": "ISBANK",
  "PayAccount": "",
  "PayMethodId": "",
  "PayType": "",
  "TradeMethodName": "İŞBANK",
  "TradeMethodShortName": ""
 },
 {
  "Identifier": "KoronaPay",
  "PayAccount": "",
  "PayMethodId": "",
  "PayType": "",
  "TradeMethodName": "KoronaPay",
  "TradeMethodShortName": ""
 },
 {
  "Identifier": "MTBank",
  "PayAccount": "",
  "PayMethodId": "",
  "PayType": "",
  "TradeMethodName": "MTBank",
  "TradeMethodShortName": "MTBank"
 },
 {
  "Identifier": "UniCreditEU",
  "PayAccount": "",
  "PayMethodId": "",
  "PayType": "",
  "TradeMethodName": "UniCredit",
  "TradeMethodShortName": "UniCredit"
 },
 {
  "Identifier": "Caissedepargne",
  "PayAccount": "",
  "PayMethodId": "",
  "PayType": "",
  "TradeMethodName": "Caisse d′Epargne",
  "TradeMethodShortName": "Caisse d′Epargne"
 },
 {
  "Identifier": "FinComBank",
  "PayAccount": "",
  "PayMethodId": "",
  "PayType": "",
  "TradeMethodName": "FinComBank",
  "TradeMethodShortName": ""
 },
 {
  "Identifier": "CashInPerson",
  "PayAccount": "",
  "PayMethodId": "",
  "PayType": "",
  "TradeMethodName": "Cash in Person",
  "TradeMethodShortName": "Cash in Person"
 },
 {
  "Identifier": "CreditBankofPeru",
  "PayAccount": "",
  "PayMethodId": "",
  "PayType": "",
  "TradeMethodName": "Credit Bank of Peru",
  "TradeMethodShortName": "BCP"
 },
 {
  "Identifier": "Inecobank",
  "PayAccount": "",
  "PayMethodId": "",
  "PayType": "",
  "TradeMethodName": "Inecobank",
  "TradeMethodShortName": ""
 },
 {
  "Identifier": "IpotekaBank",
  "PayAccount": "",
  "PayMethodId": "",
  "PayType": "",
  "TradeMethodName": "Ipoteka Bank",
  "TradeMethodShortName": ""
 },
 {
  "Identifier": "KHBank",
  "PayAccount": "",
  "PayMethodId": "",
  "PayType": "",
  "TradeMethodName": "K\u0026H Bank",
  "TradeMethodShortName": ""
 },
 {
  "Identifier": "SantanderPoland",
  "PayAccount": "",
  "PayMethodId": "",
  "PayType": "",
  "TradeMethodName": "Santander Poland",
  "TradeMethodShortName": "Santander Poland"
 },
 {
  "Identifier": "AliorBank",
  "PayAccount": "",
  "PayMethodId": "",
  "PayType": "",
  "TradeMethodName": "Alior Bank",
  "TradeMethodShortName": ""
 },
 {
  "Identifier": "BankRBK",
  "PayAccount": "",
  "PayMethodId": "",
  "PayType": "",
  "TradeMethodName": "Bank RBK",
  "TradeMethodShortName": ""
 },
 {
  "Identifier": "HomeCreditKazakhstan",
  "PayAccount": "",
  "PayMethodId": "",
  "PayType": "",
  "TradeMethodName": "Home Credit Kazakhstan",
  "TradeMethodShortName": "Home Credit Kazakhstan"
 },
 {
  "Identifier": "Papara",
  "PayAccount": "",
  "PayMethodId": "",
  "PayType": "",
  "TradeMethodName": "Papara",
  "TradeMethodShortName": "Papara"
 },
 {
  "Identifier": "PostBankNew",
  "PayAccount": "",
  "PayMethodId": "",
  "PayType": "",
  "TradeMethodName": "Post Bank",
  "TradeMethodShortName": "Post Bank"
 },
 {
  "Identifier": "StarlingBank",
  "PayAccount": "",
  "PayMethodId": "",
  "PayType": "",
  "TradeMethodName": "Starling Bank",
  "TradeMethodShortName": ""
 },
 {
  "Identifier": "mBank",
  "PayAccount": "",
  "PayMethodId": "",
  "PayType": "",
  "TradeMethodName": "mBank",
  "TradeMethodShortName": "mBank"
 },
 {
  "Identifier": "ApplePay",
  "PayAccount": "",
  "PayMethodId": "",
  "PayType": "",
  "TradeMethodName": "Apple Pay",
  "TradeMethodShortName": "Apple Pay"
 },
 {
  "Identifier": "AsakaBank",
  "PayAccount": "",
  "PayMethodId": "",
  "PayType": "",
  "TradeMethodName": "Asaka Bank",
  "TradeMethodShortName": ""
 },
 {
  "Identifier": "BANKTRANSFERRON",
  "PayAccount": "",
  "PayMethodId": "",
  "PayType": "",
  "TradeMethodName": "Bank Transfer (Romania)",
  "TradeMethodShortName": ""
 },
 {
  "Identifier": "BanescoPanama",
  "PayAccount": "",
  "PayMethodId": "",
  "PayType": "",
  "TradeMethodName": "Banesco Panama",
  "TradeMethodShortName": "Banesco Panama"
 },
 {
  "Identifier": "Interbank",
  "PayAccount": "",
  "PayMethodId": "",
  "PayType": "",
  "TradeMethodName": "Interbank",
  "TradeMethodShortName": "Interbank"
 },
 {
  "Identifier": "KICB",
  "PayAccount": "",
  "PayMethodId": "",
  "PayType": "",
  "TradeMethodName": "KICB",
  "TradeMethodShortName": ""
 },
 {
  "Identifier": "Zelle",
  "PayAccount": "",
  "PayMethodId": "",
  "PayType": "",
  "TradeMethodName": "Zelle",
  "TradeMethodShortName": "Zelle"
 },
 {
  "Identifier": "ArCA",
  "PayAccount": "",
  "PayMethodId": "",
  "PayType": "",
  "TradeMethodName": "ArCA",
  "TradeMethodShortName": ""
 },
 {
  "Identifier": "BancoDeCredito",
  "PayAccount": "",
  "PayMethodId": "",
  "PayType": "",
  "TradeMethodName": "Banco de Credito",
  "TradeMethodShortName": ""
 },
 {
  "Identifier": "BancoGeneralPanama",
  "PayAccount": "",
  "PayMethodId": "",
  "PayType": "",
  "TradeMethodName": "Banco General Panama",
  "TradeMethodShortName": "Banco General Panama"
 },
 {
  "Identifier": "Blik",
  "PayAccount": "",
  "PayMethodId": "",
  "PayType": "",
  "TradeMethodName": "Blik",
  "TradeMethodShortName": "Blik"
 },
 {
  "Identifier": "CIHBank",
  "PayAccount": "",
  "PayMethodId": "",
  "PayType": "",
  "TradeMethodName": "CIH Bank",
  "TradeMethodShortName": ""
 },
 {
  "Identifier": "Ceskasporitelna",
  "PayAccount": "",
  "PayMethodId": "",
  "PayType": "",
  "TradeMethodName": "Česká spořitelna",
  "TradeMethodShortName": "Česká spořitelna"
 },
 {
  "Identifier": "DSKBank",
  "PayAccount": "",
  "PayMethodId": "",
  "PayType": "",
  "TradeMethodName": "DSK Bank",
  "TradeMethodShortName": ""
 },
 {
  "Identifier": "Fiobanka",
  "PayAccount": "",
  "PayMethodId": "",
  "PayType": "",
  "TradeMethodName": "Fio banka",
  "TradeMethodShortName": "Fio banka"
 },
 {
  "Identifier": "HALKBANK",
  "PayAccount": "",
  "PayMethodId": "",
  "PayType": "",
  "TradeMethodName": "HalkBank",
  "TradeMethodShortName": ""
 },
 {
  "Identifier": "Humo",
  "PayAccount": "",
  "PayMethodId": "",
  "PayType": "",
  "TradeMethodName": "Humo",
  "TradeMethodShortName": ""
 },
 {
  "Identifier": "LIBERTYBANK",
  "PayAccount": "",
  "PayMethodId": "",
  "PayType": "",
  "TradeMethodName": "Liberty Bank",
  "TradeMethodShortName": ""
 },
 {
  "Identifier": "LeoBank",
  "PayAccount": "",
  "PayMethodId": "",
  "PayType": "",
  "TradeMethodName": "Leobank",
  "TradeMethodShortName": "Leobank"
 },
 {
  "Identifier": "Nurbank",
  "PayAccount": "",
  "PayMethodId": "",
  "PayType": "",
  "TradeMethodName": "Nurbank",
  "TradeMethodShortName": ""
 },
 {
  "Identifier": "PASHABANK",
  "PayAccount": "",
  "PayMethodId": "",
  "PayType": "",
  "TradeMethodName": "Pasha Bank",
  "TradeMethodShortName": ""
 },
 {
  "Identifier": "PKObank",
  "PayAccount": "",
  "PayMethodId": "",
  "PayType": "",
  "TradeMethodName": "PKO Bank",
  "TradeMethodShortName": ""
 },
 {
  "Identifier": "ParitetBank",
  "PayAccount": "",
  "PayMethodId": "",
  "PayType": "",
  "TradeMethodName": "Paritet Bank",
  "TradeMethodShortName": "Paritet Bank"
 },
 {
  "Identifier": "Payall",
  "PayAccount": "",
  "PayMethodId": "",
  "PayType": "",
  "TradeMethodName": "Payall",
  "TradeMethodShortName": "Payall"
 },
 {
  "Identifier": "Sofort",
  "PayAccount": "",
  "PayMethodId": "",
  "PayType": "",
  "TradeMethodName": "Sofort",
  "TradeMethodShortName": ""
 },
 {
  "Identifier": "Uphold",
  "PayAccount": "",
  "PayMethodId": "",
  "PayType": "",
  "TradeMethodName": "Uphold",
  "TradeMethodShortName": "Uphold"
 },
 {
  "Identifier": "Uzcard",
  "PayAccount": "",
  "PayMethodId": "",
  "PayType": "",
  "TradeMethodName": "Uzcard",
  "TradeMethodShortName": ""
 },
 {
  "Identifier": "alBaraka",
  "PayAccount": "",
  "PayMethodId": "",
  "PayType": "",
  "TradeMethodName": "alBaraka",
  "TradeMethodShortName": ""
 },
 {
  "Identifier": "ABA",
  "PayAccount": "",
  "PayMethodId": "",
  "PayType": "",
  "TradeMethodName": "ABA",
  "TradeMethodShortName": ""
 },
 {
  "Identifier": "Akbank",
  "PayAccount": "",
  "PayMethodId": "",
  "PayType": "",
  "TradeMethodName": "Akbank",
  "TradeMethodShortName": ""
 },
 {
  "Identifier": "AlliedBankLimited",
  "PayAccount": "",
  "PayMethodId": "",
  "PayType": "",
  "TradeMethodName": "Allied Bank Limited, Wholesale Branch",
  "TradeMethodShortName": ""
 },
 {
  "Identifier": "BCEL",
  "PayAccount": "",
  "PayMethodId": "",
  "PayType": "",
  "TradeMethodName": "BCEL",
  "TradeMethodShortName": "BCEL"
 },
 {
  "Identifier": "BankTransferMena",
  "PayAccount": "",
  "PayMethodId": "",
  "PayType": "",
  "TradeMethodName": "Bank Transfer (Middle East)",
  "TradeMethodShortName": ""
 },
 {
  "Identifier": "BosBank",
  "PayAccount": "",
  "PayMethodId": "",
  "PayType": "",
  "TradeMethodName": "BOS Bank",
  "TradeMethodShortName": ""
 },
 {
  "Identifier": "COMMERCIALBANKKZT",
  "PayAccount": "",
  "PayMethodId": "",
  "PayType": "",
  "TradeMethodName": "Commercial bank Kyrgyzstan",
  "TradeMethodShortName": ""
 },
 {
  "Identifier": "CSOB",
  "PayAccount": "",
  "PayMethodId": "",
  "PayType": "",
  "TradeMethodName": "ČSOB",
  "TradeMethodShortName": "ČSOB"
 },
 {
  "Identifier": "EasypaisaPK",
  "PayAccount": "",
  "PayMethodId": "",
  "PayType": "",
  "TradeMethodName": "Easypaisa-PK Only",
  "TradeMethodShortName": "Easypaisa-PK Only"
 },
 {
  "Identifier": "Fibabanka",
  "PayAccount": "",
  "PayMethodId": "",
  "PayType": "",
  "TradeMethodName": "Fibabanka",
  "TradeMethodShortName": ""
 },
 {
  "Identifier": "IdeaBank",
  "PayAccount": "",
  "PayMethodId": "",
  "PayType": "",
  "TradeMethodName": "Idea Bank",
  "TradeMethodShortName": ""
 },
 {
  "Identifier": "LloydsBank",
  "PayAccount": "",
  "PayMethodId": "",
  "PayType": "",
  "TradeMethodName": "Lloyds Bank",
  "TradeMethodShortName": "Lloyds Bank"
 },
 {
  "Identifier": "NayaPay",
  "PayAccount": "",
  "PayMethodId": "",
  "PayType": "",
  "TradeMethodName": "NayaPay",
  "TradeMethodShortName": ""
 },
 {
  "Identifier": "Nequi",
  "PayAccount": "",
  "PayMethodId": "",
  "PayType": "",
  "TradeMethodName": "Nequi",
  "TradeMethodShortName": "Nequi"
 },
 {
  "Identifier": "Oschadbank",
  "PayAccount": "",
  "PayMethodId": "",
  "PayType": "",
  "TradeMethodName": "Oschadbank",
  "TradeMethodShortName": "Oschadbank"
 },
 {
  "Identifier": "QNB",
  "PayAccount": "",
  "PayMethodId": "",
  "PayType": "",
  "TradeMethodName": "QNB",
  "TradeMethodShortName": ""
 },
 {
  "Identifier": "RussianStandardBank",
  "PayAccount": "",
  "PayMethodId": "",
  "PayType": "",
  "TradeMethodName": "Russian Standard Bank",
  "TradeMethodShortName": "Russian Standard Bank"
 },
 {
  "Identifier": "StandardChartered",
  "PayAccount": "",
  "PayMethodId": "",
  "PayType": "",
  "TradeMethodName": "Standard Chartered Bank",
  "TradeMethodShortName": ""
 },
 {
  "Identifier": "TransferenciaACH",
  "PayAccount": "",
  "PayMethodId": "",
  "PayType": "",
  "TradeMethodName": "Transferencia ACH (Panamá)",
  "TradeMethodShortName": ""
 },
 {
  "Identifier": "UnitedBulgarianBank",
  "PayAccount": "",
  "PayMethodId": "",
  "PayType": "",
  "TradeMethodName": "United Bulgarian Bank (UBB)",
  "TradeMethodShortName": ""
 },
 {
  "Identifier": "m10",
  "PayAccount": "",
  "PayMethodId": "",
  "PayType": "",
  "TradeMethodName": "m10",
  "TradeMethodShortName": "m10"
 },
 {
  "Identifier": "ACLEDA",
  "PayAccount": "",
  "PayMethodId": "",
  "PayType": "",
  "TradeMethodName": "ACLEDA",
  "TradeMethodShortName": ""
 },
 {
  "Identifier": "ALIPAY",
  "PayAccount": "",
  "PayMethodId": "",
  "PayType": "",
  "TradeMethodName": "Alipay",
  "TradeMethodShortName": "Alipay"
 },
 {
  "Identifier": "AbsolutBank",
  "PayAccount": "",
  "PayMethodId": "",
  "PayType": "",
  "TradeMethodName": "Absolut Bank",
  "TradeMethodShortName": ""
 },
 {
  "Identifier": "AgroBank",
  "PayAccount": "",
  "PayMethodId": "",
  "PayType": "",
  "TradeMethodName": "Agrobank",
  "TradeMethodShortName": ""
 },
 {
  "Identifier": "ArmEconomBank",
  "PayAccount": "",
  "PayMethodId": "",
  "PayType": "",
  "TradeMethodName": "ArmEconomBank",
  "TradeMethodShortName": ""
 },
 {
  "Identifier": "AsiaUnitedBank",
  "PayAccount": "",
  "PayMethodId": "",
  "PayType": "",
  "TradeMethodName": "Asia United Bank",
  "TradeMethodShortName": ""
 },
 {
  "Identifier": "AzerTurkBank",
  "PayAccount": "",
  "PayMethodId": "",
  "PayType": "",
  "TradeMethodName": "Azer Turk Bank",
  "TradeMethodShortName": "Azer Turk Bank"
 },
 {
  "Identifier": "BancolombiaSA",
  "PayAccount": "",
  "PayMethodId": "",
  "PayType": "",
  "TradeMethodName": "Bancolombia S.A",
  "TradeMethodShortName": "Bancolombia S.A"
 },
 {
  "Identifier": "Bancontact",
  "PayAccount": "",
  "PayMethodId": "",
  "PayType": "",
  "TradeMethodName": "Bancontact",
  "TradeMethodShortName": ""
 },
 {
  "Identifier": "Banesco",
  "PayAccount": "",
  "PayMethodId": "",
  "PayType": "",
  "TradeMethodName": "Banesco",
  "TradeMethodShortName": "Banesco"
 },
 {
  "Identifier": "BanistmoPanama",
  "PayAccount": "",
  "PayMethodId": "",
  "PayType": "",
  "TradeMethodName": "Banistmo Panama",
  "TradeMethodShortName": "Banistmo Panama"
 },
 {
  "Identifier": "BankIndia",
  "PayAccount": "",
  "PayMethodId": "",
  "PayType": "",
  "TradeMethodName": "Bank Transfer (India)",
  "TradeMethodShortName": "Bank Transfer (India)"
 },
 {
  "Identifier": "BankPekao",
  "PayAccount": "",
  "PayMethodId": "",
  "PayType": "",
  "TradeMethodName": "Bank Pekao",
  "TradeMethodShortName": ""
 },
 {
  "Identifier": "Bankera",
  "PayAccount": "",
  "PayMethodId": "",
  "PayType": "",
  "TradeMethodName": "Bankera",
  "TradeMethodShortName": "Bankera"
 },
 {
  "Identifier": "BankofAmerica",
  "PayAccount": "",
  "PayMethodId": "",
  "PayType": "",
  "TradeMethodName": "Bank of America",
  "TradeMethodShortName": "Bank of America"
 },
 {
  "Identifier": "CIMBNiaga",
  "PayAccount": "",
  "PayMethodId": "",
  "PayType": "",
  "TradeMethodName": "CIMB Niaga",
  "TradeMethodShortName": ""
 },
 {
  "Identifier": "Cashapp",
  "PayAccount": "",
  "PayMethodId": "",
  "PayType": "",
  "TradeMethodName": "Cash app",
  "TradeMethodShortName": "Cash app"
 },
 {
  "Identifier": "ChinggisKhaanBank",
  "PayAccount": "",
  "PayMethodId": "",
  "PayType": "",
  "TradeMethodName": "Chinggis Khaan Bank",
  "TradeMethodShortName": "Chinggis Khaan Bank"
 },
 {
  "Identifier": "EQbank",
  "PayAccount": "",
  "PayMethodId": "",
  "PayType": "",
  "TradeMethodName": "EQ Bank",
  "TradeMethodShortName": "EQ Bank"
 },
 {
  "Identifier": "FasterPayments",
  "PayAccount": "",
  "PayMethodId": "",
  "PayType": "",
  "TradeMethodName": "Faster Payments",
  "TradeMethodShortName": ""
 },
 {
  "Identifier": "MKBBank",
  "PayAccount": "",
  "PayMethodId": "",
  "PayType": "",
  "TradeMethodName": "MKB Bank",
  "TradeMethodShortName": ""
 },
 {
  "Identifier": "Maybank",
  "PayAccount": "",
  "PayMethodId": "",
  "PayType": "",
  "TradeMethodName": "Maybank",
  "TradeMethodShortName": ""
 },
 {
  "Identifier": "MeezanBank",
  "PayAccount": "",
  "PayMethodId": "",
  "PayType": "",
  "TradeMethodName": "Meezan Bank",
  "TradeMethodShortName": ""
 },
 {
  "Identifier": "Monzo",
  "PayAccount": "",
  "PayMethodId": "",
  "PayType": "",
  "TradeMethodName": "Monzo",
  "TradeMethodShortName": ""
 },
 {
  "Identifier": "OTPBankRussia",
  "PayAccount": "",
  "PayMethodId": "",
  "PayType": "",
  "TradeMethodName": "OTP",
  "TradeMethodShortName": "OTP"
 },
 {
  "Identifier": "Payme",
  "PayAccount": "",
  "PayMethodId": "",
  "PayType": "",
  "TradeMethodName": "PayMe",
  "TradeMethodShortName": "PayMe"
 },
 {
  "Identifier": "Paytm",
  "PayAccount": "",
  "PayMethodId": "",
  "PayType": "",
  "TradeMethodName": "Paytm",
  "TradeMethodShortName": "Paytm"
 },
 {
  "Identifier": "PhonePe",
  "PayAccount": "",
  "PayMethodId": "",
  "PayType": "",
  "TradeMethodName": "PhonePe",
  "TradeMethodShortName": "PhonePe"
 },
 {
  "Identifier": "Pix",
  "PayAccount": "",
  "PayMethodId": "",
  "PayType": "",
  "TradeMethodName": "Pix",
  "TradeMethodShortName": "Pix"
 },
 {
  "Identifier": "RSKBANK",
  "PayAccount": "",
  "PayMethodId": "",
  "PayType": "",
  "TradeMethodName": "RSK Bank",
  "TradeMethodShortName": ""
 },
 {
  "Identifier": "Raast",
  "PayAccount": "",
  "PayMethodId": "",
  "PayType": "",
  "TradeMethodName": "Raast",
  "TradeMethodShortName": ""
 },
 {
  "Identifier": "SadaPay",
  "PayAccount": "",
  "PayMethodId": "",
  "PayType": "",
  "TradeMethodName": "SadaPay",
  "TradeMethodShortName": ""
 },
 {
  "Identifier": "Satispay",
  "PayAccount": "",
  "PayMethodId": "",
  "PayType": "",
  "TradeMethodName": "Satispay",
  "TradeMethodShortName": ""
 },
 {
  "Identifier": "TDbank",
  "PayAccount": "",
  "PayMethodId": "",
  "PayType": "",
  "TradeMethodName": "TD Bank",
  "TradeMethodShortName": "TD Bank"
 },
 {
  "Identifier": "TransBank",
  "PayAccount": "",
  "PayMethodId": "",
  "PayType": "",
  "TradeMethodName": "Trans Bank",
  "TradeMethodShortName": "Trans Bank"
 },
 {
  "Identifier": "UPI",
  "PayAccount": "",
  "PayMethodId": "",
  "PayType": "",
  "TradeMethodName": "UPI",
  "TradeMethodShortName": "UPI"
 },
 {
  "Identifier": "UniCreditBulbank",
  "PayAccount": "",
  "PayMethodId": "",
  "PayType": "",
  "TradeMethodName": "UniCredit Bulbank",
  "TradeMethodShortName": ""
 },
 {
  "Identifier": "Vodafonecash",
  "PayAccount": "",
  "PayMethodId": "",
  "PayType": "",
  "TradeMethodName": "Vodafone cash",
  "TradeMethodShortName": "Vodafone cash"
 },
 {
  "Identifier": "Zinli",
  "PayAccount": "",
  "PayMethodId": "",
  "PayType": "",
  "TradeMethodName": "Zinli",
  "TradeMethodShortName": ""
 },
 {
  "Identifier": "izibank",
  "PayAccount": "",
  "PayMethodId": "",
  "PayType": "",
  "TradeMethodName": "Izibank",
  "TradeMethodShortName": ""
 }
]